{
  "nolocationroad": "Il n'y a pas d'emplacement dans cette route.",
  "unnamedroad": "Route sans nom",
  "locationalreadyregistered": "Cet emplacement est déjà enregistré.",
  "registerlocation": "Enregistrement d'un emplacement à X: %s, Z: %s.",
  "currentlyon": "Actuellement sur : %s.",
  "blocksprediction": "%s\nCela prendra %s blocs",
  "thengoto": "%s puis aller à\n",
  "noarguments": "Vous n'avez pas exécuté la commande avec des arguments. Veuillez l'exécuter à nouveau avec les arguments %s.",
  "example": "Exemple : %s",
  "toomanyarguments": "Vous avez exécuté la commande avec trop d'arguments. Veuillez l'exécuter à nouveau avec les arguments %s.",
  "invalidcoordinates": "Coordonnées invalides, merci d'essayer à une autre position.",
  "finallygoto": "Puis aller à X: %s Z: %s.",
  "registerroadarguments": "(facultatif) nom de la route > <coordonnées des emplacements sous X Y Z avec espace entre les arguments",
  "registeredroad": "Vous avez enregistré une nouvelle route.",
  "notonaroad": "Vous n'êtes actuellement dans aucune rue.",
  "noargumentsother": "Vous n'avez pas exécuté la commande avec des arguments. Veuillez l'exécuter à nouveau avec les arguments %s.",
  "load": "Chargement en cours, cela pourrait prendre du temps.",
  "pathnotfound": "Chemin non trouvé.",
  "outdated": "Mojang Maps est obsolète, veuillez télécharger la version la plus récente à l'adresse : %s.",
  "calcins": "Calculé en %s secondes.",
  "navigation": "Navigation",
  "nonodesfound": "No locations found. Try registering a road first."
}
